{
  "posts": [
    {
      "id": 1,
      "title": "json-server",
      "author": "typicode"
    }
  ],
  "comments": [
    {
      "id": 1,
      "body": "some comment",
      "postId": 1
    }
  ],
  "profile": [
    {
      "name": "typicode"
    }
  ],
  "movies": [
    {
      "id": 4,
      "title": "Kapitan",
      "year": 3,
      "duration": "4"
    },
    {
      "id": "ad",
      "title": "123",
      "year": "123"
    },
    {
      "id": 3,
      "title": "ad",
      "year": "123",
      "duration": "123"
    },
    {
      "id": "asd",
      "title": "123",
      "year": "123"
    }
  ],
  "rooms": [
    {
      "id": 1
    }
  ],
  "shows": [
    {
      "id": 1
    }
  ]
}